actionspytoolkit/__init__.py
actionspytoolkit/__version__.py
actionspytoolkit/logging.py
actionspytoolkit/status.py
actionspytoolkit-2020.0.0.dist-info/LICENSE
actionspytoolkit-2020.0.0.dist-info/METADATA
actionspytoolkit-2020.0.0.dist-info/WHEEL
actionspytoolkit-2020.0.0.dist-info/top_level.txt
actionspytoolkit-2020.0.0.dist-info/RECORD
