Metadata-Version: 2.1
Name: actionspytoolkit
Version: 2020.0.0
Summary: GitHub Actions Development Tools in Python.
Home-page: https://github.com/Lnk2past/actions-pytoolkit
Author: Lnk2past
License: MIT
Platform: UNKNOWN
